jax_fid/__init__.py
jax_fid/__main__.py
jax_fid/fid.py
jax_fid/inception.py
jax_fid/utils.py
jax_fid-0.0.2.dist-info/LICENSE
jax_fid-0.0.2.dist-info/METADATA
jax_fid-0.0.2.dist-info/WHEEL
jax_fid-0.0.2.dist-info/entry_points.txt
jax_fid-0.0.2.dist-info/top_level.txt
jax_fid-0.0.2.dist-info/RECORD
