Metadata-Version: 2.1
Name: jax-fid
Version: 0.0.2
Summary: FID computation in Jax/Flax.
Home-page: https://github.com/matthias-wright/jax-fid
Author: Matthias Wright
License: Apache License 2.0
Platform: UNKNOWN
Requires-Python: >=3.6
Requires-Dist: numpy (==1.19.5)
Requires-Dist: requests (==2.23.0)
Requires-Dist: jax
Requires-Dist: jaxlib
Requires-Dist: flax
Requires-Dist: Pillow (==7.1.2)
Requires-Dist: tqdm (==4.60.0)
Requires-Dist: scipy
Provides-Extra: testing
Requires-Dist: pytest ; extra == 'testing'
